mordor/__init__.py
mordor/app_env.py
mordor/mordor.py
mordor/bin/host_tools.txt
mordor/bin/init_host.sh
mordor/bin/install_packages.sh
mordor/bin/run_dispatcher.sh
mordor/libs/__init__.py
mordor/libs/app_config.py
mordor/libs/app_manifest.py
mordor/libs/config.py
mordor/libs/host_config.py
mordor/libs/tools.py
mordor2-0.0.60.dist-info/LICENSE
mordor2-0.0.60.dist-info/METADATA
mordor2-0.0.60.dist-info/WHEEL
mordor2-0.0.60.dist-info/entry_points.txt
mordor2-0.0.60.dist-info/top_level.txt
mordor2-0.0.60.dist-info/RECORD
