Metadata-Version: 2.1
Name: mordor2
Version: 0.0.60
Summary: Python Deployment Tool
Home-page: https://github.com/stonezhong/mordor
Author: Stone Zhong
Author-email: stonezhong@hotmail.com
License: MIT
Classifier: License :: OSI Approved :: MIT License
Classifier: Programming Language :: Python :: 2
Classifier: Programming Language :: Python :: 3
License-File: LICENSE
Requires-Dist: PyYAML
Requires-Dist: Jinja2
